[
    {
        "id_texto": 1,
        "resultado": {
            "errores_ortografia_puntual": {
                "error_1": [
                    "errados, la → errados. La"
                ],
                "error_2": [
                    "conversacion, para → conversacion. Para"
                ],
                "error_3": [
                    "oficinas un → oficinas, un"
                ],
                "error_4": [
                    "no y → no, y"
                ],
                "error_5": [
                    "contrato, todo → contrato. Todo"
                ],
                "error_6": [
                    "regulado, si → regulado si"
                ],
                "error_7": [
                    "amenaza pero → amenaza, pero"
                ],
                "error_8": [
                    "trabajador, la → trabajador. La"
                ],
                "error_9": [
                    "literalmente) solo → literalmente), solo"
                ],
                "error_10": [
                    "vitalmente) → vitalmente)."
                ],
                "error_11": [
                    "pensar, que → pensar que"
                ],
                "error_12": [
                    "realidad, nos → realidad. Nos"
                ],
                "error_13": [
                    "algo la → algo, la"
                ],
                "error_14": [
                    "reduce, ahora → reduce. Ahora"
                ],
                "error_15": [
                    "comodidad, estas → comodidad. Estas"
                ],
                "error_16": [
                    "lado, por → lado. Por"
                ],
                "error_17": [
                    "alternativo si → alternativo, si"
                ],
                "error_18": [
                    "opcion → opcion."
                ]
            }
        }
    },
    {
        "id_texto": 2,
        "resultado": {
            "errores_ortografia_puntual": {
                "error_1": [
                    "preocupantes, el → preocupantes: el"
                ],
                "error_2": [
                    "virtual, limita → virtual limita"
                ],
                "error_3": [
                    "sistema?. → sistema?"
                ],
                "error_4": [
                    "latinoamérica, se → latinoamérica se"
                ],
                "error_5": [
                    "niño, se → niño se"
                ],
                "error_6": [
                    "Uno, aprendizaje → Uno aprendizaje"
                ],
                "error_7": [
                    "familiar, que → familiar que"
                ],
                "error_8": [
                    "dos, aprendizaje → dos aprendizaje"
                ],
                "error_9": [
                    "cognitivo, son → cognitivo son"
                ],
                "error_10": [
                    "selectivo, basado → selectivo basado"
                ],
                "error_11": [
                    "categorías, desarrollan → categorías desarrollan"
                ],
                "error_12": [
                    "íntegro, que → íntegro que"
                ],
                "error_13": [
                    "habilidades, ya → habilidades ya"
                ],
                "error_14": [
                    "ya sea, a → ya sea a"
                ],
                "error_15": [
                    "debe, a → debe a"
                ],
                "error_16": [
                    "niño, sin → niño. Sin"
                ],
                "error_17": [
                    "ya que, según → ya que según"
                ],
                "error_18": [
                    "también, las → también las"
                ],
                "error_19": [
                    "actualmente, vacunarse → actualmente vacunarse"
                ],
                "error_20": [
                    "ello, que → ello que"
                ],
                "error_21": [
                    "ellos, puedan → ellos puedan"
                ],
                "error_22": [
                    "sociales, y → sociales y"
                ]
            }
        }
    },
    {
        "id_texto": 3,
        "resultado": {
            "errores_ortografia_puntual": {
                "error_1": [
                    "este, frente → este frente"
                ],
                "error_2": [
                    "salud, es → salud es"
                ],
                "error_3": [
                    "medidas, en → medidas en"
                ],
                "error_4": [
                    "salud, que → salud que"
                ],
                "error_5": [
                    "Por esto el → Por esto, el"
                ],
                "error_6": [
                    "día; lo → día, lo"
                ],
                "error_7": [
                    "involucrados; por → involucrados, por"
                ],
                "error_8": [
                    "manera, análisis → manera. Análisis"
                ],
                "error_9": [
                    "concluir, que → concluir que"
                ],
                "error_10": [
                    "ambiente ,como → ambiente, como"
                ]
            }
        }
    },
    {
        "id_texto": 4,
        "resultado": {
            "errores_ortografia_puntual": {
                "error_1": [
                    "ciudades, debe → ciudades debe"
                ],
                "error_2": [
                    "específica el → específica, el"
                ],
                "error_3": [
                    "Chile, la → Chile: la"
                ],
                "error_4": [
                    "India en → India, en"
                ],
                "error_5": [
                    "parte tendríamos → parte, tendríamos"
                ],
                "error_6": [
                    "casas, también → casas. También"
                ],
                "error_7": [
                    "salud, puede → salud puede"
                ],
                "error_8": [
                    "dicen \"las → dicen: \"las"
                ],
                "error_9": [
                    "Aunque, no → Aunque no"
                ]
            }
        }
    },
    {
        "id_texto": 5,
        "resultado": {
            "errores_ortografia_puntual": {
                "error_1": [
                    "nombre, y → nombre y"
                ],
                "error_2": [
                    "entonces, implica → entonces implica"
                ],
                "error_3": [
                    "liberal, ella → liberal. Ella"
                ],
                "error_4": [
                    "relevantes, y → relevantes y"
                ]
            }
        }
    },
    {
        "id_texto": 6,
        "resultado": {
            "errores_ortografia_puntual": {
                "error_1": [
                    "laboral, han → laboral han"
                ],
                "error_2": [
                    "cuarentenas evitando → cuarentenas,evitando"
                ]
            }
        }
    },
    {
        "id_texto": 7,
        "resultado": {
            "errores_ortografia_puntual": {
                "error_1": [
                    "cultural, que → cultural que"
                ],
                "error_2": [
                    "cultural, los → cultural los"
                ],
                "error_3": [
                    "presentes. Ya → presentes, Ya"
                ],
                "error_4": [
                    "país. De → país, De"
                ],
                "error_5": [
                    "individualidad, y → individualidad y"
                ],
                "error_6": [
                    "Y, siguiendo → Y siguiendo"
                ]
            }
        }
    },
    {
        "id_texto": 8,
        "resultado": {
            "errores_ortografia_puntual": {
                "error_1": [
                    "Chile el → Chile, el"
                ],
                "error_2": [
                    "hogar. Sin → hogar, sin"
                ],
                "error_3": [
                    "trabajo a → trabajo, a"
                ],
                "error_4": [
                    "laboralmente. Causando → laboralmente, causando"
                ],
                "error_5": [
                    "tranquilo, que → tranquilo que"
                ],
                "error_6": [
                    "laboral, puede → laboral puede"
                ],
                "error_7": [
                    "cuidado, por → cuidado por"
                ]
            }
        }
    },
    {
        "id_texto": 9,
        "resultado": {
            "errores_ortografia_puntual": {
                "error_1": [
                    "seguro, de → seguro de"
                ],
                "error_2": [
                    "diaras dejando → diaras, dejando"
                ],
                "error_3": [
                    "actualidad existen → actualidad, existen"
                ]
            }
        }
    },
    {
        "id_texto": 10,
        "resultado": {
            "errores_ortografia_puntual": {
                "error_1": [
                    "presenciales, con → presenciales con"
                ],
                "error_2": [
                    "estudiantes, y → estudiantes y"
                ],
                "error_3": [
                    "y, además → y además"
                ],
                "error_4": [
                    "menores, por → menores; por"
                ],
                "error_5": [
                    "aprendizaje, así → aprendizaje así"
                ],
                "error_6": [
                    "también, para → también para"
                ],
                "error_7": [
                    "ello, que → ello que"
                ]
            }
        }
    },
    {
        "id_texto": 11,
        "resultado": {
            "errores_ortografia_puntual": {
                "error_1": [
                    "Fratelli Tutti el → Fratelli Tutti, el"
                ],
                "error_2": [
                    "cristiana, no → cristiana. No"
                ],
                "error_3": [
                    "ajenas, no → ajenas. No"
                ],
                "error_4": [
                    "sobretodo, practicar → sobretodo practicar"
                ],
                "error_5": [
                    "tiránica El → tiránica. El"
                ]
            }
        }
    },
    {
        "id_texto": 12,
        "resultado": {
            "errores_ortografia_puntual": {
                "error_1": [
                    "muscular, o → muscular o"
                ],
                "error_2": [
                    "mesa, y → mesa y"
                ],
                "error_3": [
                    "información, es → información es"
                ],
                "error_4": [
                    "de en → de, en"
                ],
                "error_5": [
                    "efecto ser → efecto, ser"
                ],
                "error_6": [
                    "efectivos, no → efectivos no"
                ],
                "error_7": [
                    "población, ni → población ni"
                ],
                "error_8": [
                    "honesta, y → honesta y"
                ]
            }
        }
    },
    {
        "id_texto": 13,
        "resultado": {
            "errores_ortografia_puntual": {
                "error_1": [
                    "comenzar a → comenzar, a"
                ],
                "error_2": [
                    "COVID-19, para → COVID-19. Para"
                ],
                "error_3": [
                    "marzo este → marzo, este"
                ],
                "error_4": [
                    "virus el → virus, el"
                ],
                "error_5": [
                    "mundial, esto → mundial. Esto"
                ],
                "error_6": [
                    "cuarentena algunas → cuarentena, algunas"
                ],
                "error_7": [
                    "ultimo el → ultimo, el"
                ],
                "error_8": [
                    "1980, sin → 1980. Sin"
                ],
                "error_9": [
                    "sin embargo el → sin embargo, el"
                ],
                "error_10": [
                    "mundial, por → mundial. Por"
                ],
                "error_11": [
                    "por esto la → por esto, la"
                ],
                "error_12": [
                    "octubre, esto → octubre. Esto"
                ],
                "error_13": [
                    "esto surgen → esto, surgen"
                ],
                "error_14": [
                    "posibles aun → posibles, aun"
                ],
                "error_15": [
                    "lado muchas → lado, muchas"
                ],
                "error_16": [
                    "voto que → voto, que"
                ],
                "error_17": [
                    "asintomaticamente, esto → asintomaticamente. Esto"
                ],
                "error_18": [
                    "síntoma, esto → síntoma. Esto"
                ],
                "error_19": [
                    "forma, puede → forma. Puede"
                ],
                "error_20": [
                    "Ahora bien en → Ahora bien, en"
                ],
                "error_21": [
                    "conclusión todos → conclusión, todos"
                ],
                "error_22": [
                    "octubre, porque → octubre porque"
                ],
                "error_23": [
                    "cambio, en → cambio. En"
                ]
            }
        }
    },
    {
        "id_texto": 14,
        "resultado": {
            "errores_ortografia_puntual": {
                "error_1": [
                    "Pero, ¿Qué → Pero ¿Qué"
                ],
                "error_2": [
                    "Suprema?,¿ → Suprema?"
                ]
            }
        }
    },
    {
        "id_texto": 15,
        "resultado": {
            "errores_ortografia_puntual": {
                "error_1": [
                    "población lo → población. Lo"
                ],
                "error_2": [
                    "COVID- 19 sin → COVID- 19. Sin"
                ],
                "error_3": [
                    "Sin embargo se → Sin embargo, se"
                ],
                "error_4": [
                    "alterado no → alterado. No"
                ],
                "error_5": [
                    "lado el → lado, el"
                ],
                "error_6": [
                    "personas el → personas. El"
                ],
                "error_7": [
                    "salud ya → salud, ya"
                ],
                "error_8": [
                    "laboral sin → laboral. Sin"
                ],
                "error_9": [
                    "Sin embargo con → Sin embargo, con"
                ]
            }
        }
    },
    {
        "id_texto": 16,
        "resultado": {
            "errores_ortografia_puntual": {
                "error_1": [
                    "virtuales, permiten → virtuales permiten"
                ]
            }
        }
    },
    {
        "id_texto": 17,
        "resultado": {
            "errores_ortografia_puntual": {
                "error_1": [
                    "que en → que, en"
                ],
                "error_2": [
                    "escolar, el → escolar el"
                ],
                "error_3": [
                    "constantemente, mejora → constantemente mejora"
                ],
                "error_4": [
                    "esta, por → esta por"
                ],
                "error_5": [
                    "anterior, nuestros → anterior nuestros"
                ],
                "error_6": [
                    "deportes, es → deportes es"
                ],
                "error_7": [
                    "importante, para → importante para"
                ],
                "error_8": [
                    "que, a → que a"
                ],
                "error_9": [
                    "tanto, como → tanto como"
                ],
                "error_10": [
                    "esto, es → esto es"
                ],
                "error_11": [
                    "tipo, para → tipo para"
                ]
            }
        }
    },
    {
        "id_texto": 18,
        "resultado": {
            "errores_ortografia_puntual": {
                "error_1": [
                    "países, que → países que"
                ],
                "error_2": [
                    "tiempo, que → tiempo que"
                ],
                "error_3": [
                    "humano, se → humano se"
                ],
                "error_4": [
                    "y especificamente → y, especificamente"
                ],
                "error_5": [
                    "y por → y, por"
                ],
                "error_6": [
                    "ello, que → ello que"
                ],
                "error_7": [
                    "laborales q → laborales q."
                ]
            }
        }
    },
    {
        "id_texto": 19,
        "resultado": {
            "errores_ortografia_puntual": {
                "error_1": [
                    "mundo → mundo."
                ]
            }
        }
    },
    {
        "id_texto": 20,
        "resultado": {
            "errores_ortografia_puntual": {
                "error_1": [
                    "personas, y → personas y"
                ],
                "error_2": [
                    "meses la → meses, la"
                ],
                "error_3": [
                    "vuelto además → vuelto, además"
                ],
                "error_4": [
                    "pobre lamentablemente → pobre, lamentablemente"
                ],
                "error_5": [
                    "lamentablemente es → lamentablemente, es"
                ],
                "error_6": [
                    "recursos, y → recursos y"
                ],
                "error_7": [
                    "En cambio la → En cambio, la"
                ],
                "error_8": [
                    "santiario, y → santiario y"
                ],
                "error_9": [
                    "encerrados temas → encerrados, temas"
                ]
            }
        }
    }
]